airflow/providers/microsoft/azure/__init__.py
airflow/providers/microsoft/azure/get_provider_info.py
airflow/providers/microsoft/azure/utils.py
airflow/providers/microsoft/azure/version_compat.py
airflow/providers/microsoft/azure/fs/__init__.py
airflow/providers/microsoft/azure/fs/adls.py
airflow/providers/microsoft/azure/fs/msgraph.py
airflow/providers/microsoft/azure/hooks/__init__.py
airflow/providers/microsoft/azure/hooks/adx.py
airflow/providers/microsoft/azure/hooks/asb.py
airflow/providers/microsoft/azure/hooks/base_azure.py
airflow/providers/microsoft/azure/hooks/batch.py
airflow/providers/microsoft/azure/hooks/container_instance.py
airflow/providers/microsoft/azure/hooks/container_registry.py
airflow/providers/microsoft/azure/hooks/container_volume.py
airflow/providers/microsoft/azure/hooks/cosmos.py
airflow/providers/microsoft/azure/hooks/data_factory.py
airflow/providers/microsoft/azure/hooks/data_lake.py
airflow/providers/microsoft/azure/hooks/fileshare.py
airflow/providers/microsoft/azure/hooks/msgraph.py
airflow/providers/microsoft/azure/hooks/powerbi.py
airflow/providers/microsoft/azure/hooks/synapse.py
airflow/providers/microsoft/azure/hooks/wasb.py
airflow/providers/microsoft/azure/log/__init__.py
airflow/providers/microsoft/azure/log/wasb_task_handler.py
airflow/providers/microsoft/azure/operators/__init__.py
airflow/providers/microsoft/azure/operators/adls.py
airflow/providers/microsoft/azure/operators/adx.py
airflow/providers/microsoft/azure/operators/asb.py
airflow/providers/microsoft/azure/operators/batch.py
airflow/providers/microsoft/azure/operators/container_instances.py
airflow/providers/microsoft/azure/operators/cosmos.py
airflow/providers/microsoft/azure/operators/data_factory.py
airflow/providers/microsoft/azure/operators/msgraph.py
airflow/providers/microsoft/azure/operators/powerbi.py
airflow/providers/microsoft/azure/operators/synapse.py
airflow/providers/microsoft/azure/operators/wasb_delete_blob.py
apache_airflow_providers_microsoft_azure-12.10.2.dist-info/entry_points.txt
apache_airflow_providers_microsoft_azure-12.10.2.dist-info/licenses/LICENSE
apache_airflow_providers_microsoft_azure-12.10.2.dist-info/licenses/NOTICE
apache_airflow_providers_microsoft_azure-12.10.2.dist-info/WHEEL
apache_airflow_providers_microsoft_azure-12.10.2.dist-info/METADATA
apache_airflow_providers_microsoft_azure-12.10.2.dist-info/RECORD
