Metadata-Version: 2.4
Name: apache-airflow-providers-microsoft-azure
Version: 12.10.2
Summary: Provider package apache-airflow-providers-microsoft-azure for Apache Airflow
Keywords: airflow-provider,microsoft.azure,airflow,integration
Author-email: Apache Software Foundation <dev@airflow.apache.org>
Maintainer-email: Apache Software Foundation <dev@airflow.apache.org>
Requires-Python: >=3.10
License-Expression: Apache-2.0
Classifier: Development Status :: 5 - Production/Stable
Classifier: Environment :: Console
Classifier: Environment :: Web Environment
Classifier: Intended Audience :: Developers
Classifier: Intended Audience :: System Administrators
Classifier: Framework :: Apache Airflow
Classifier: Framework :: Apache Airflow :: Provider
Classifier: Programming Language :: Python :: 3.10
Classifier: Programming Language :: Python :: 3.11
Classifier: Programming Language :: Python :: 3.12
Classifier: Programming Language :: Python :: 3.13
Classifier: Topic :: System :: Monitoring
License-File: LICENSE
License-File: NOTICE
Requires-Dist: apache-airflow>=2.11.0
Requires-Dist: apache-airflow-providers-common-compat>=1.12.0
Requires-Dist: adlfs>=2023.10.0
Requires-Dist: azure-batch>=8.0.0
Requires-Dist: azure-cosmos>=4.6.0
Requires-Dist: azure-mgmt-cosmosdb>=3.0.0
Requires-Dist: azure-datalake-store>=0.0.45
Requires-Dist: azure-identity>=1.3.1
Requires-Dist: azure-keyvault-secrets>=4.1.0
Requires-Dist: azure-mgmt-datalake-store>=0.5.0
Requires-Dist: azure-mgmt-resource>=2.2.0
Requires-Dist: azure-storage-blob>=12.26.0
Requires-Dist: azure-mgmt-storage>=16.0.0
Requires-Dist: azure-storage-file-share>=12.7.0
Requires-Dist: azure-servicebus>=7.12.1
Requires-Dist: azure-synapse-spark>=0.2.0
Requires-Dist: azure-synapse-artifacts>=0.17.0
Requires-Dist: azure-storage-file-datalake>=12.9.1
Requires-Dist: azure-kusto-data>=4.1.0,!=4.6.0,!=5.0.0
Requires-Dist: azure-mgmt-datafactory>=2.0.0
Requires-Dist: azure-mgmt-containerregistry>=8.0.0
Requires-Dist: azure-mgmt-containerinstance>=10.1.0
Requires-Dist: msgraph-core>=1.3.3
Requires-Dist: msgraphfs>=0.3.0
Requires-Dist: microsoft-kiota-http>=1.9.4,<2.0.0
Requires-Dist: microsoft-kiota-serialization-json>=1.9.4
Requires-Dist: microsoft-kiota-serialization-text>=1.9.4
Requires-Dist: microsoft-kiota-abstractions>=1.9.4,<2.0.0
Requires-Dist: microsoft-kiota-authentication-azure>=1.9.4,<2.0.0
Requires-Dist: msal-extensions>=1.3.0
Requires-Dist: apache-airflow-providers-amazon ; extra == "amazon"
Requires-Dist: apache-airflow-providers-oracle ; extra == "oracle"
Requires-Dist: apache-airflow-providers-sftp ; extra == "sftp"
Project-URL: Bug Tracker, https://github.com/apache/airflow/issues
Project-URL: Changelog, https://airflow.apache.org/docs/apache-airflow-providers-microsoft-azure/12.10.2/changelog.html
Project-URL: Documentation, https://airflow.apache.org/docs/apache-airflow-providers-microsoft-azure/12.10.2
Project-URL: Mastodon, https://fosstodon.org/@airflow
Project-URL: Slack Chat, https://s.apache.org/airflow-slack
Project-URL: Source Code, https://github.com/apache/airflow
Project-URL: YouTube, https://www.youtube.com/channel/UCSXwxpWZQ7XZ1WL3wqevChA/
Provides-Extra: amazon
Provides-Extra: oracle
Provides-Extra: sftp
